django_queue_manager/API.py
django_queue_manager/__init__.py
django_queue_manager/admin.py
django_queue_manager/apps.py
django_queue_manager/models.py
django_queue_manager/server_manager.py
django_queue_manager/service_manager.py
django_queue_manager/shell.py
django_queue_manager/task_manager.py
django_queue_manager/worker.py
django_queue_manager/worker_manager.py
django_queue_manager/migrations/0001_initial.py
django_queue_manager/migrations/__init__.py
django_queue_manager/utilities/__init__.py
django_queue_manager/utilities/loggers.py
django_queue_manager-1.3.9.dist-info/LICENSE
django_queue_manager-1.3.9.dist-info/METADATA
django_queue_manager-1.3.9.dist-info/WHEEL
django_queue_manager-1.3.9.dist-info/top_level.txt
django_queue_manager-1.3.9.dist-info/RECORD
