Metadata-Version: 2.1
Name: django-queue-manager
Version: 1.3.9
Summary: A simple app that provides a Message Queue System using a socket as broker, this app, make you able to manage an ordered queue of tasks (with calling a simple queuing function form API).Simple to setup, easy to manage and scalable, the queue can be remotized to another server,you can use multiple istance of the application, and easly manage multiple broker and relatives queues.This app, will integrate into your DB backend and serves three table with the states of the queue.
Home-page: http://www.fardellasimone.com/
Author: Fardella Simone
Author-email: fardella.simone@gmail.com
License: GNU GPLv3
Platform: UNKNOWN
Classifier: Environment :: Web Environment
Classifier: Framework :: Django
Classifier: Intended Audience :: Developers
Classifier: License :: OSI Approved :: GNU General Public License v3 (GPLv3)
Classifier: Operating System :: OS Independent
Classifier: Programming Language :: Python
Classifier: Programming Language :: Python :: 3.4
Classifier: Programming Language :: Python :: 3.5
Classifier: Programming Language :: Python :: 3.6
Classifier: Topic :: Internet :: WWW/HTTP
Classifier: Topic :: Internet :: WWW/HTTP :: Dynamic Content
